odoo/addons/queued_purchase_picking_notify/README.rst
odoo/addons/queued_purchase_picking_notify/__init__.py
odoo/addons/queued_purchase_picking_notify/__manifest__.py
odoo/addons/queued_purchase_picking_notify/i18n/es.po
odoo/addons/queued_purchase_picking_notify/models/__init__.py
odoo/addons/queued_purchase_picking_notify/models/in_picking_activity_notify.py
odoo/addons/queued_purchase_picking_notify/models/in_picking_mail_notify.py
odoo/addons/queued_purchase_picking_notify/models/in_picking_note_notify.py
odoo/addons/queued_purchase_picking_notify/models/in_picking_notify_mixin.py
odoo/addons/queued_purchase_picking_notify/models/purchase_order.py
odoo/addons/queued_purchase_picking_notify/models/purchase_order_type.py
odoo/addons/queued_purchase_picking_notify/models/stock_picking.py
odoo/addons/queued_purchase_picking_notify/readme/CONFIGURE.md
odoo/addons/queued_purchase_picking_notify/readme/CONTRIBUTORS.md
odoo/addons/queued_purchase_picking_notify/readme/DESCRIPTION.md
odoo/addons/queued_purchase_picking_notify/readme/ROADMAP.md
odoo/addons/queued_purchase_picking_notify/security/ir.model.access.csv
odoo/addons/queued_purchase_picking_notify/security/queued_picking_notify_security.xml
odoo/addons/queued_purchase_picking_notify/static/description/icon.png
odoo/addons/queued_purchase_picking_notify/static/description/index.html
odoo/addons/queued_purchase_picking_notify/tests/__init__.py
odoo/addons/queued_purchase_picking_notify/tests/test_queued_purchase_picking_notify.py
odoo/addons/queued_purchase_picking_notify/views/purchase_order_type_view.xml
odoo/addons/queued_purchase_picking_notify/views/stock_picking.xml
odoo_addon_queued_purchase_picking_notify-17.0.1.1.0.dist-info/METADATA
odoo_addon_queued_purchase_picking_notify-17.0.1.1.0.dist-info/WHEEL
odoo_addon_queued_purchase_picking_notify-17.0.1.1.0.dist-info/top_level.txt
odoo_addon_queued_purchase_picking_notify-17.0.1.1.0.dist-info/RECORD
