Metadata-Version: 2.1
Name: odoo-addon-queued_purchase_picking_notify
Version: 17.0.1.1.0
Requires-Python: >=3.10
Requires-Dist: odoo-addon-queued_purchase_notify>=17.0dev,<17.1dev
Requires-Dist: odoo>=17.0a,<17.1dev
Summary: Schedule email/logs/activities notificacions on purchase pickings
Home-page: https://github.com/sygel-technology/sy-stock-logistics-workflow
License: AGPL-3
Author: Sygel, Odoo Community Association (OCA)
Author-email: support@odoo-community.org
Classifier: Programming Language :: Python
Classifier: Framework :: Odoo
Classifier: Framework :: Odoo :: 17.0
Classifier: License :: OSI Approved :: GNU Affero General Public License v3
